[
  {
    "arguments": [
      "/usr/bin/gcc",
      "-Wall",
      "-Wextra",
      "-Werror",
      "-O0",
      "-g",
      "-c",
      "-o",
      "build/editor.o",
      "src/editor.c"
    ],
    "directory": "/home/yousef/projects/gedit",
    "file": "/home/yousef/projects/gedit/src/editor.c",
    "output": "/home/yousef/projects/gedit/build/editor.o"
  },
  {
    "arguments": [
      "/usr/bin/gcc",
      "-Wall",
      "-Wextra",
      "-Werror",
      "-O0",
      "-g",
      "-c",
      "-o",
      "build/gedit.o",
      "src/gedit.c"
    ],
    "directory": "/home/yousef/projects/gedit",
    "file": "/home/yousef/projects/gedit/src/gedit.c",
    "output": "/home/yousef/projects/gedit/build/gedit.o"
  },
  {
    "arguments": [
      "/usr/bin/gcc",
      "-Wall",
      "-Wextra",
      "-Werror",
      "-O0",
      "-g",
      "-c",
      "-o",
      "build/term.o",
      "src/term.c"
    ],
    "directory": "/home/yousef/projects/gedit",
    "file": "/home/yousef/projects/gedit/src/term.c",
    "output": "/home/yousef/projects/gedit/build/term.o"
  }
]
